jra_tools/__init__.py
jra_tools/database/__init__.py
jra_tools/database/bao_importer.py
jra_tools/database/db_checker.py
jra_tools/database/predict_factory.py
jra_tools/database/predict_race_factory.py
jra_tools/database/schedule.py
jra_tools/machine_learning/__init__.py
jra_tools/machine_learning/util.py
jra_tools/machine_learning/entity/jrdbdummies.py
jra_tools/machine_learning/entity/labelutil.py
jra_tools/machine_learning/infrastructure/mysql_loader.py
jra_tools/machine_learning/interface_adapter/iioloader.py
jra_tools/machine_learning/interface_adapter/input_creator.py
jra_tools/machine_learning/interface_adapter/ispecified_loader.py
jra_tools/machine_learning/interface_adapter/label_creator.py
jra_tools/machine_learning/interface_adapter/payout_creator.py
jra_tools/machine_learning/interface_adapter/quarter_kaisai_query.py
jra_tools/machine_learning/interface_adapter/training_kaisai_query.py
jra_tools/machine_learning/usecase/category_data.py
jra_tools/machine_learning/usecase/converter.py
jra_tools/machine_learning/usecase/icreator.py
jra_tools/machine_learning/usecase/iquery.py
jra_tools/machine_learning/usecase/training_tool.py
jra_tools-0.0.17.dist-info/METADATA
jra_tools-0.0.17.dist-info/WHEEL
jra_tools-0.0.17.dist-info/top_level.txt
jra_tools-0.0.17.dist-info/RECORD
