Metadata-Version: 2.4
Name: jra-tools
Version: 0.0.17
Summary: Data Analisys Tools for JRDB
Author-email: Requrd <requrd1989@gmail.com>
Project-URL: Homepage, https://github.com/astroripple/jra-tools
Project-URL: Bug Tracker, https://github.com/astroripple/jra-tools/issues
Classifier: Programming Language :: Python :: 3
Classifier: License :: OSI Approved :: MIT License
Classifier: Operating System :: OS Independent
Requires-Python: >=3.12
Requires-Dist: jrdb-model>=0.2.10
Requires-Dist: beautifulsoup4>=4.11.1
Requires-Dist: scikit-learn>=1.6.1
Requires-Dist: numpy>1.24.4
Requires-Dist: lxml>=4.9.0
Requires-Dist: requests>=2.31.0
Requires-Dist: aiohttp>=3.8.5
Requires-Dist: tensorflow>=2.18.0
